bad_apple_turtle/__init__.py
bad_apple_turtle/bad_apple_turtle.py
bad_apple_turtle/vector_video.py
bad_apple_turtle-2.1.1b0.dist-info/LICENSE
bad_apple_turtle-2.1.1b0.dist-info/METADATA
bad_apple_turtle-2.1.1b0.dist-info/WHEEL
bad_apple_turtle-2.1.1b0.dist-info/entry_points.txt
bad_apple_turtle-2.1.1b0.dist-info/top_level.txt
bad_apple_turtle-2.1.1b0.dist-info/RECORD
