Metadata-Version: 2.1
Name: bad-apple-turtle
Version: 2.1.1b0
Summary: A script that converts videos into a format playable by a Python turtle.
Home-page: https://github.com/CaptainD1/bad-apple-turtle
Author: Devan Plaga
Author-email: legohavend@gmail.com
Project-URL: Bug Tracker, https://github.com/CaptainD1/bad-apple-turtle/issues
Classifier: Programming Language :: Python :: 3
Classifier: License :: OSI Approved :: MIT License
Classifier: Operating System :: OS Independent
Requires-Python: >=3.9
License-File: LICENSE
Requires-Dist: opencv-python
Provides-Extra: vlc
Requires-Dist: python-vlc ; extra == 'vlc'
Provides-Extra: yt-dlp
Requires-Dist: yt-dlp ; extra == 'yt-dlp'
